MANIFEST.in
setup.py
django_singlerecord.egg-info/PKG-INFO
django_singlerecord.egg-info/SOURCES.txt
django_singlerecord.egg-info/dependency_links.txt
django_singlerecord.egg-info/not-zip-safe
django_singlerecord.egg-info/top_level.txt
singlerecord/__init__.py
singlerecord/admin.py
singlerecord/models.py