Metadata-Version: 1.0
Name: django-singlerecord
Version: 0.1.1
Summary: Abstraction for models with only one record for Django
Home-page: http://github.com/tavaresb/django-singlerecord
Author: Bruno Tavares
Author-email: eu@brunotavares.net
License: UNKNOWN
Platform: UNKNOWN
Classifier: Development Status :: 3 - Alpha
Classifier: Environment :: Web Environment
Classifier: Intended Audience :: Developers
Classifier: License :: OSI Approved :: BSD License
Classifier: Operating System :: OS Independent
Classifier: Programming Language :: Python
Classifier: Framework :: Django
